quantumhall_matrixelements/__init__.py
quantumhall_matrixelements/diagnostic.py
quantumhall_matrixelements/exchange_hankel.py
quantumhall_matrixelements/exchange_legendre.py
quantumhall_matrixelements/planewave.py
quantumhall_matrixelements-1.0.0.dist-info/licenses/LICENSE
quantumhall_matrixelements-1.0.0.dist-info/METADATA
quantumhall_matrixelements-1.0.0.dist-info/WHEEL
quantumhall_matrixelements-1.0.0.dist-info/top_level.txt
quantumhall_matrixelements-1.0.0.dist-info/RECORD
