Metadata-Version: 2.4
Name: quantumhall_matrixelements
Version: 1.0.0
Summary: Landau-level plane-wave form factors and exchange kernels for quantum Hall systems.
Author: Sparsh Mishra
Author-email: Tobias Wolf <public@wolft.xyz>
License: MIT
Project-URL: Homepage, https://github.com/wolft/quantumhall_matrixelements
Project-URL: Issues, https://github.com/wolft/quantumhall_matrixelements/issues
Keywords: quantum Hall,matrix elements,form factors,exchange kernels,Landau levels
Classifier: Programming Language :: Python :: 3
Classifier: Programming Language :: Python :: 3.10
Classifier: Programming Language :: Python :: 3.11
Classifier: Programming Language :: Python :: 3.12
Classifier: License :: OSI Approved :: MIT License
Classifier: Intended Audience :: Science/Research
Classifier: Topic :: Scientific/Engineering :: Physics
Requires-Python: >=3.10
License-File: LICENSE
Requires-Dist: numpy>=1.26
Requires-Dist: scipy>=1.11
Requires-Dist: hankel>=1.2
Provides-Extra: dev
Requires-Dist: pytest>=8.0; extra == "dev"
Requires-Dist: pytest-cov>=5.0; extra == "dev"
Requires-Dist: ruff>=0.5.0; extra == "dev"
Requires-Dist: mypy>=1.10; extra == "dev"
Requires-Dist: build; extra == "dev"
Requires-Dist: twine; extra == "dev"
Dynamic: license-file
